Metadata-Version: 1.2
Name: spantestpypi
Version: 0.1.0
Summary: A brief description of your package
Home-page: UNKNOWN
Author: Your Name
Author-email: your_email@example.com
License: BSD License
Platform: UNKNOWN
Classifier: Programming Language :: Python :: 3
Classifier: Programming Language :: Python :: 3.6
Classifier: Programming Language :: Python :: 3.7
Classifier: License :: OSI Approved :: MIT License
Classifier: Operating System :: MacOS
Requires-Python: >=3.6
